cicv/__init__.py
cicv/config.py
cicv/source.py
cicv/utils.py
cicv-0.0.3.dist-info/LICENSE
cicv-0.0.3.dist-info/METADATA
cicv-0.0.3.dist-info/WHEEL
cicv-0.0.3.dist-info/top_level.txt
cicv-0.0.3.dist-info/RECORD
